{
	"__credit": "Generated using Animated Java (https://animated-java.dev/)",
	"textures": {
		"0": "minecraft:entity/steambird"
	},
	"elements": [
		{
			"faces": {
				"north": {"uv": [8.375, 2.125, 8.5, 2.3125], "texture": "#0"},
				"east": {"uv": [8.0625, 2.125, 8.375, 2.3125], "texture": "#0"},
				"south": {"uv": [8.8125, 2.125, 8.9375, 2.3125], "texture": "#0"},
				"west": {"uv": [8.5, 2.125, 8.8125, 2.3125], "texture": "#0"},
				"up": {"uv": [8.5, 2.125, 8.375, 1.8125], "texture": "#0"},
				"down": {"uv": [8.625, 1.8125, 8.5, 2.125], "texture": "#0"}
			},
			"to": [7.5, 5.7, 9.6],
			"from": [6.7, 4.5, 7.6],
			"rotation": {"angle": 0, "axis": "y", "origin": [8.4, 3, 7.6]}
		},
		{
			"faces": {
				"north": {"uv": [5.6875, 4.1875, 5.8125, 4.25], "texture": "#0"},
				"east": {"uv": [5.5, 4.1875, 5.6875, 4.25], "texture": "#0"},
				"south": {"uv": [6, 4.1875, 6.125, 4.25], "texture": "#0"},
				"west": {"uv": [5.8125, 4.1875, 6, 4.25], "texture": "#0"},
				"up": {"uv": [5.8125, 4.1875, 5.6875, 4], "texture": "#0"},
				"down": {"uv": [5.9375, 4, 5.8125, 4.1875], "texture": "#0"}
			},
			"to": [7.5, 6.1, 9.2],
			"from": [6.7, 5.7, 8],
			"rotation": {"angle": 0, "axis": "y", "origin": [8.4, 3, 7.6]}
		},
		{
			"faces": {
				"north": {"uv": [3, 5.6875, 3.125, 5.75], "texture": "#0"},
				"east": {"uv": [2.8125, 5.6875, 3, 5.75], "texture": "#0"},
				"south": {"uv": [3.3125, 5.6875, 3.4375, 5.75], "texture": "#0"},
				"west": {"uv": [3.125, 5.6875, 3.3125, 5.75], "texture": "#0"},
				"up": {"uv": [3.125, 5.6875, 3, 5.5], "texture": "#0"},
				"down": {"uv": [3.25, 5.5, 3.125, 5.6875], "texture": "#0"}
			},
			"to": [7.5, 4.5, 9.2],
			"from": [6.7, 4.1, 8],
			"rotation": {"angle": 0, "axis": "y", "origin": [8.4, 3, 7.6]}
		},
		{
			"faces": {
				"north": {"uv": [5.6875, 0.75, 5.8125, 0.8125], "texture": "#0"},
				"east": {"uv": [5.5, 0.75, 5.6875, 0.8125], "texture": "#0"},
				"south": {"uv": [6, 0.75, 6.125, 0.8125], "texture": "#0"},
				"west": {"uv": [5.8125, 0.75, 6, 0.8125], "texture": "#0"},
				"up": {"uv": [5.8125, 0.75, 5.6875, 0.5625], "texture": "#0"},
				"down": {"uv": [5.9375, 0.5625, 5.8125, 0.75], "texture": "#0"}
			},
			"to": [7.525, 4.8, 10.8],
			"from": [6.725, 4.4, 9.6],
			"rotation": {"angle": 0, "axis": "y", "origin": [8.4, 3, 7.6]}
		},
		{
			"faces": {
				"north": {"uv": [7.1875, 7.8125, 7.3125, 7.9375], "texture": "#0"},
				"east": {"uv": [6.75, 7.8125, 7.1875, 7.9375], "texture": "#0"},
				"south": {"uv": [7.75, 7.8125, 7.875, 7.9375], "texture": "#0"},
				"west": {"uv": [7.3125, 7.8125, 7.75, 7.9375], "texture": "#0"},
				"up": {"uv": [7.3125, 7.8125, 7.1875, 7.375], "texture": "#0"},
				"down": {"uv": [7.4375, 7.375, 7.3125, 7.8125], "texture": "#0"}
			},
			"to": [7.5, 5.5, 12.4],
			"from": [6.7, 4.7, 9.6],
			"rotation": {"angle": 0, "axis": "y", "origin": [8.4, 3, 7.6]}
		}
	],
	"display": {
		"head": {
			"translation": [0, 5.6, 0],
			"scale": [4, 4, 4],
			"rotation": [0, 0, 0]
		}
	}
}